synapseconvert/__init__.py
synapseconvert/downconvert.py
synapseconvert/upconvert.py
synapseconvert-1.0.0.dist-info/LICENSE
synapseconvert-1.0.0.dist-info/METADATA
synapseconvert-1.0.0.dist-info/WHEEL
synapseconvert-1.0.0.dist-info/entry_points.txt
synapseconvert-1.0.0.dist-info/top_level.txt
synapseconvert-1.0.0.dist-info/RECORD
