Metadata-Version: 2.1
Name: synapseconvert
Version: 1.0.0
Summary: Tools for converting Synapse RTP JSON to spreadsheet and back.
Home-page: https://github.com/BiblicalStory/synapseconvert
Author: Samuel Baylis
Author-email: request@biblicalstory.org
License: MIT
Classifier: Programming Language :: Python :: 3
Classifier: License :: OSI Approved :: MIT License
Classifier: Operating System :: OS Independent
Requires-Python: >=3.8
License-File: LICENSE
Requires-Dist: pandas
Requires-Dist: openpyxl
